{
    "id": 1459,
    "keyType": "COORDGRID",
    "valType": "OBJ",
    "defaultString": "null",
    "defaultInt": 8245,
    "size": 15,
    "params": {
        "16385": 20617,
        "16386": 20618,
        "16387": 20619,
        "16388": 20620,
        "32769": 20623,
        "32770": 20624,
        "32771": 20625,
        "49153": 20626,
        "49154": 20627,
        "49155": 20628,
        "65537": 20629,
        "81921": 20630,
        "81922": 20631,
        "81923": 20632,
        "98305": 20633
    }
}