{
    "id": 846,
    "keyType": "OBJ",
    "valType": "INTEGER",
    "defaultString": "null",
    "defaultInt": 2147483647,
    "size": 181,
    "params": {
        "3095": 13,
        "3096": 28,
        "3097": 43,
        "3099": 63,
        "3100": 83,
        "3101": 98,
        "1205": 0,
        "1277": 4,
        "1321": 5,
        "1291": 6,
        "1307": 14,
        "1203": 15,
        "1279": 19,
        "1323": 20,
        "1293": 21,
        "1309": 29,
        "1207": 30,
        "1281": 34,
        "1325": 35,
        "1295": 36,
        "1311": 44,
        "1209": 50,
        "1285": 54,
        "1329": 55,
        "1299": 56,
        "1315": 64,
        "1211": 70,
        "1287": 74,
        "1331": 75,
        "1301": 76,
        "1317": 84,
        "1213": 85,
        "1289": 89,
        "1333": 90,
        "1303": 91,
        "1319": 99,
        "1422": 2,
        "1337": 9,
        "1351": 0,
        "1375": 10,
        "1420": 17,
        "1335": 24,
        "1349": 16,
        "1363": 25,
        "1424": 32,
        "1339": 39,
        "1353": 31,
        "1365": 40,
        "1428": 52,
        "1343": 59,
        "1355": 51,
        "1369": 60,
        "1430": 72,
        "1345": 79,
        "1357": 71,
        "1371": 80,
        "1432": 87,
        "1347": 94,
        "1359": 86,
        "1373": 95,
        "1103": 11,
        "1075": 16,
        "1087": 16,
        "1117": 18,
        "1101": 26,
        "1067": 31,
        "1081": 31,
        "1115": 33,
        "1105": 41,
        "1069": 46,
        "1083": 46,
        "1119": 48,
        "1109": 61,
        "1071": 66,
        "1085": 66,
        "1121": 68,
        "1111": 81,
        "1073": 86,
        "1091": 86,
        "1123": 88,
        "1113": 96,
        "1079": 99,
        "1093": 99,
        "1127": 99,
        "1139": 3,
        "1155": 7,
        "1173": 8,
        "1189": 12,
        "4819": 4,
        "1137": 18,
        "1153": 22,
        "1175": 23,
        "1191": 27,
        "4820": 19,
        "1141": 33,
        "1157": 37,
        "1177": 38,
        "1193": 42,
        "1539": 34,
        "1143": 53,
        "1159": 57,
        "1181": 58,
        "1197": 62,
        "4822": 54,
        "1145": 73,
        "1161": 77,
        "1183": 78,
        "1199": 82,
        "4823": 74,
        "1147": 88,
        "1163": 92,
        "1185": 93,
        "1201": 97,
        "4824": 89,
        "864": 7,
        "819": 4,
        "39": 5,
        "1794": 4,
        "863": 22,
        "820": 19,
        "40": 20,
        "7225": 17,
        "865": 37,
        "821": 34,
        "41": 35,
        "2370": 36,
        "866": 57,
        "822": 54,
        "42": 55,
        "867": 77,
        "823": 74,
        "43": 75,
        "868": 92,
        "824": 89,
        "44": 90,
        "9375": 3,
        "9420": 6,
        "9377": 18,
        "9423": 23,
        "9378": 33,
        "9425": 36,
        "9379": 53,
        "9427": 56,
        "9380": 73,
        "9429": 76,
        "9381": 88,
        "9431": 91,
        "4540": 26,
        "4544": 49,
        "9416": 59,
        "19570": 6,
        "19572": 21,
        "19574": 36,
        "19576": 56,
        "19578": 76,
        "19580": 91,
        "13538": 45,
        "13539": 47,
        "13540": 49,
        "13541": 51,
        "13542": 53,
        "13543": 55,
        "13544": 57,
        "13545": 59,
        "13546": 61,
        "13547": 63,
        "13548": 65,
        "13549": 67,
        "13550": 69,
        "13551": 71,
        "13552": 73,
        "13553": 75,
        "13554": 77,
        "13555": 79,
        "13556": 81,
        "13557": 83,
        "13558": 85,
        "13559": 87,
        "13560": 89,
        "13561": 91,
        "13562": 93
    }
}