{
    "id": 29228,
    "name": "null",
    "width": 2,
    "height": 2,
    "interactType": 1,
    "blockProjectile": false,
    "int1": 1,
    "clipType": -1,
    "nonFlatShading": false,
    "modelClipped": false,
    "animationId": -1,
    "int2": 16,
    "ambient": 0,
    "contrast": 0,
    "actions": [
        "null",
        "null",
        "null",
        "null",
        "null"
    ],
    "mapIconId": -1,
    "mapSceneId": -1,
    "isRotated": false,
    "clipped": true,
    "modelSizeX": 128,
    "modelHeight": 128,
    "modelSizeY": 128,
    "offsetX": 0,
    "offsetHeight": 0,
    "offsetY": 0,
    "boolean2": false,
    "breakRouteFinding": false,
    "int3": -1,
    "transformVarbit": 5374,
    "transformVarp": -1,
    "ambientSoundId": -1,
    "int7": 0,
    "int5": 0,
    "int6": 0,
    "boolean3": true,
    "transforms": [
        11761,
        13621,
        13628,
        13635,
        29362,
        29363,
        29364,
        29365,
        29366,
        29367,
        29368,
        29369,
        29370,
        29371,
        29372,
        29373,
        29374,
        29375,
        29376,
        29377,
        29378,
        29379,
        29380,
        29381,
        29382,
        29383,
        29384,
        29385,
        29386,
        29387,
        29388,
        29389,
        29390,
        29391,
        29392,
        29393,
        29394,
        29395,
        29396,
        29397,
        29398,
        29399,
        29400,
        29401,
        29402,
        29403,
        29404,
        29405,
        29406,
        29407,
        29408,
        29409,
        29410,
        29411,
        29412,
        29413,
        29414,
        29415,
        29416,
        29417,
        29418,
        29419,
        29420,
        29421,
        -1
    ],
    "params": {
    }
}