{
    "id": 1021,
    "field2079": -1,
    "field2082": 0,
    "field2083": 0,
    "frameCount": 9,
    "field2091": false,
    "field2092": 5,
    "shield": -1,
    "weapon": -1,
    "field2095": 99,
    "field2096": -1,
    "field2097": -1,
    "field2078": 2,
    "frameLengths": [
        2,
        3,
        3,
        3,
        6,
        6,
        2,
        2,
        2
    ],
    "frameIds": [
        32309263,
        32309264,
        32309265,
        32309266,
        32309267,
        32309268,
        32309269,
        32309270,
        32309271
    ],
    "chatFrameIds": [
    ]
}