{
    "id": 1193,
    "field2079": -1,
    "field2082": 0,
    "field2083": 0,
    "frameCount": 44,
    "field2091": true,
    "field2092": 5,
    "shield": 0,
    "weapon": 3669,
    "field2095": 3,
    "field2096": 1,
    "field2097": 1,
    "field2078": 2,
    "frameLengths": [
        4,
        4,
        4,
        4,
        4,
        4,
        4,
        4,
        4,
        4,
        4,
        4,
        4,
        4,
        4,
        4,
        4,
        4,
        4,
        4,
        4,
        4,
        4,
        4,
        4,
        4,
        4,
        4,
        4,
        4,
        4,
        4,
        4,
        4,
        4,
        4,
        4,
        4,
        4,
        4,
        4,
        4,
        4,
        4
    ],
    "frameIds": [
        19267730,
        19267741,
        19267752,
        19267757,
        19267758,
        19267759,
        19267760,
        19267761,
        19267762,
        19267731,
        19267732,
        19267733,
        19267734,
        19267735,
        19267736,
        19267737,
        19267738,
        19267739,
        19267740,
        19267742,
        19267743,
        19267744,
        19267745,
        19267734,
        19267735,
        19267736,
        19267737,
        19267738,
        19267739,
        19267740,
        19267742,
        19267743,
        19267744,
        19267745,
        19267746,
        19267747,
        19267748,
        19267749,
        19267750,
        19267751,
        19267753,
        19267754,
        19267755,
        19267756
    ],
    "chatFrameIds": [
    ]
}