{
    "id": 1764,
    "field2079": -1,
    "field2082": 0,
    "field2083": 0,
    "frameCount": -1,
    "field2091": false,
    "field2092": 5,
    "shield": 0,
    "weapon": 0,
    "field2095": 99,
    "field2096": -1,
    "field2097": -1,
    "field2078": 2,
    "frameLengths": [
        4,
        4,
        3,
        10,
        3,
        2,
        3,
        10,
        4,
        3,
        10
    ],
    "frameIds": [
        17563697,
        17563700,
        17563701,
        17563702,
        17563703,
        17563704,
        17563705,
        17563706,
        17563707,
        17563698,
        17563699
    ],
    "chatFrameIds": [
    ]
}