{
    "id": 2251,
    "field2079": -1,
    "field2082": 0,
    "field2083": 0,
    "frameCount": -1,
    "field2091": false,
    "field2092": 5,
    "shield": -1,
    "weapon": -1,
    "field2095": 99,
    "field2096": -1,
    "field2097": -1,
    "field2078": 2,
    "frameLengths": [
        5,
        4,
        4,
        4,
        5,
        4,
        4,
        4
    ],
    "frameIds": [
        16580623,
        16580624,
        16580625,
        16580626,
        16580627,
        16580628,
        16580629,
        16580630
    ],
    "chatFrameIds": [
    ]
}