{
    "id": 2362,
    "field2079": -1,
    "field2082": 0,
    "field2083": 0,
    "frameCount": -1,
    "field2091": false,
    "field2092": 5,
    "shield": -1,
    "weapon": -1,
    "field2095": 99,
    "field2096": -1,
    "field2097": -1,
    "field2078": 2,
    "frameLengths": [
        5,
        5,
        4,
        4,
        4,
        4,
        4,
        4,
        4,
        4,
        4,
        4,
        5,
        5,
        5,
        31
    ],
    "frameIds": [
        917504,
        917513,
        917514,
        917515,
        917516,
        917517,
        917518,
        917519,
        917520,
        917506,
        917507,
        917508,
        917509,
        917510,
        917511,
        917512
    ],
    "chatFrameIds": [
    ]
}