{
    "id": 3014,
    "field2079": -1,
    "field2082": 0,
    "field2083": 0,
    "frameCount": -1,
    "field2091": false,
    "field2092": 5,
    "shield": -1,
    "weapon": -1,
    "field2095": 99,
    "field2096": -1,
    "field2097": -1,
    "field2078": 2,
    "frameLengths": [
        1,
        1,
        2,
        2,
        2,
        2,
        2,
        2,
        2,
        2,
        2,
        2,
        2,
        2,
        2,
        2,
        2,
        2,
        2,
        2,
        2
    ],
    "frameIds": [
        5111821,
        5111811,
        5111812,
        5111829,
        5111820,
        5111823,
        5111824,
        5111819,
        5111809,
        5111828,
        5111814,
        5111826,
        5111817,
        5111813,
        5111808,
        5111827,
        5111816,
        5111818,
        5111810,
        5111825,
        5111822
    ],
    "chatFrameIds": [
    ]
}