{
    "id": 3302,
    "field2079": -1,
    "field2082": 0,
    "field2083": 0,
    "frameCount": 23,
    "field2091": false,
    "field2092": 5,
    "shield": 0,
    "weapon": 7926,
    "field2095": 99,
    "field2096": -1,
    "field2097": -1,
    "field2078": 2,
    "frameLengths": [
        4,
        4,
        3,
        4,
        4,
        4,
        4,
        5,
        5,
        5,
        5,
        5,
        5,
        5,
        5,
        5,
        5,
        5,
        5,
        4,
        4,
        4,
        4
    ],
    "frameIds": [
        19988536,
        19988547,
        19988553,
        19988554,
        19988555,
        19988556,
        19988557,
        19988558,
        19988559,
        19988537,
        19988538,
        19988539,
        19988540,
        19988541,
        19988542,
        19988543,
        19988544,
        19988545,
        19988546,
        19988548,
        19988549,
        19988550,
        19988551
    ],
    "chatFrameIds": [
    ]
}