{
    "id": 355,
    "field2079": -1,
    "field2082": 0,
    "field2083": 0,
    "frameCount": -1,
    "field2091": false,
    "field2092": 5,
    "shield": -1,
    "weapon": -1,
    "field2095": 99,
    "field2096": -1,
    "field2097": -1,
    "field2078": 2,
    "frameLengths": [
        3,
        3,
        3,
        3,
        3,
        3,
        3,
        3,
        3,
        3,
        3,
        3,
        3,
        3,
        3,
        3,
        3,
        3,
        3,
        3,
        3
    ],
    "frameIds": [
        31981672,
        31981683,
        31981686,
        31981687,
        31981688,
        31981689,
        31981690,
        31981691,
        31981692,
        31981673,
        31981674,
        31981675,
        31981676,
        31981677,
        31981678,
        31981679,
        31981680,
        31981681,
        31981682,
        31981684,
        31981685
    ],
    "chatFrameIds": [
    ]
}