{
    "id": 3566,
    "field2079": -1,
    "field2082": 0,
    "field2083": 0,
    "frameCount": -1,
    "field2091": false,
    "field2092": 5,
    "shield": 0,
    "weapon": 8149,
    "field2095": 99,
    "field2096": -1,
    "field2097": -1,
    "field2078": 2,
    "frameLengths": [
        7,
        7,
        7,
        7,
        7,
        7,
        7,
        7,
        6,
        5,
        6,
        7,
        6,
        6,
        6,
        6,
        6,
        6,
        6,
        6,
        6,
        6,
        7,
        7,
        7,
        7,
        7,
        6,
        7,
        6,
        5,
        5,
        5,
        5
    ],
    "frameIds": [
        16384000,
        16384025,
        16384036,
        16384042,
        16384043,
        16384044,
        16384045,
        16384046,
        16384047,
        16384015,
        16384016,
        16384017,
        16384018,
        16384019,
        16384020,
        16384021,
        16384022,
        16384023,
        16384024,
        16384026,
        16384027,
        16384028,
        16384029,
        16384030,
        16384031,
        16384032,
        16384033,
        16384034,
        16384035,
        16384037,
        16384038,
        16384039,
        16384040,
        16384041
    ],
    "chatFrameIds": [
    ]
}