{
    "id": 3571,
    "field2079": -1,
    "field2082": 0,
    "field2083": 0,
    "frameCount": -1,
    "field2091": true,
    "field2092": 5,
    "shield": -1,
    "weapon": -1,
    "field2095": 99,
    "field2096": -1,
    "field2097": -1,
    "field2078": 2,
    "frameLengths": [
        4,
        4,
        4,
        4,
        8,
        4,
        4,
        4,
        4,
        4,
        4
    ],
    "frameIds": [
        15859732,
        15859735,
        15859736,
        15859737,
        15859738,
        15859739,
        15859740,
        15859741,
        15859742,
        15859733,
        15859734
    ],
    "chatFrameIds": [
    ]
}