{
    "id": 426,
    "field2079": -1,
    "field2082": 0,
    "field2083": 0,
    "frameCount": -1,
    "field2091": false,
    "field2092": 6,
    "shield": -1,
    "weapon": -1,
    "field2095": 99,
    "field2096": -1,
    "field2097": -1,
    "field2078": 2,
    "frameLengths": [
        4,
        4,
        4,
        4,
        15,
        10,
        5,
        4,
        4,
        4
    ],
    "frameIds": [
        13697054,
        13697056,
        13697057,
        13697058,
        13697059,
        13697060,
        13697061,
        13697062,
        13697063,
        13697055
    ],
    "chatFrameIds": [
    ]
}