{
    "id": 4720,
    "field2079": -1,
    "field2082": 0,
    "field2083": 0,
    "frameCount": -1,
    "field2091": false,
    "field2092": 8,
    "shield": -1,
    "weapon": -1,
    "field2095": 99,
    "field2096": -1,
    "field2097": -1,
    "field2078": 2,
    "frameLengths": [
        3,
        3,
        3,
        3,
        3,
        3,
        3,
        3,
        3,
        3,
        3,
        3,
        3,
        3,
        3,
        3
    ],
    "frameIds": [
        80871462,
        80871473,
        80871484,
        80871495,
        80871506,
        80871516,
        80871517,
        80871518,
        80871519,
        80871463,
        80871464,
        80871465,
        80871466,
        80871467,
        80871468,
        80871469
    ],
    "chatFrameIds": [
    ]
}