{
    "id": 4736,
    "field2079": -1,
    "field2082": 0,
    "field2083": 0,
    "frameCount": -1,
    "field2091": false,
    "field2092": 5,
    "shield": -1,
    "weapon": -1,
    "field2095": 99,
    "field2096": -1,
    "field2097": -1,
    "field2078": 2,
    "frameLengths": [
        5,
        5,
        5,
        5,
        5,
        5,
        5,
        5,
        5,
        5,
        5,
        5,
        5,
        5,
        5,
        5,
        5,
        5,
        5,
        5,
        5,
        5,
        5,
        5,
        5,
        5,
        5,
        5,
        5
    ],
    "frameIds": [
        76218380,
        76218413,
        76218424,
        76218425,
        76218426,
        76218427,
        76218428,
        76218429,
        76218430,
        76218403,
        76218404,
        76218405,
        76218406,
        76218407,
        76218408,
        76218409,
        76218410,
        76218411,
        76218412,
        76218414,
        76218415,
        76218416,
        76218417,
        76218418,
        76218419,
        76218420,
        76218421,
        76218422,
        76218423
    ],
    "chatFrameIds": [
    ]
}