{
    "id": 4938,
    "field2079": -1,
    "field2082": 0,
    "field2083": 0,
    "frameCount": -1,
    "field2091": false,
    "field2092": 5,
    "shield": -1,
    "weapon": -1,
    "field2095": 99,
    "field2096": -1,
    "field2097": -1,
    "field2078": 2,
    "frameLengths": [
        4,
        4,
        4,
        4,
        4,
        4,
        4,
        4,
        4,
        4,
        4,
        4,
        4,
        4,
        4,
        4,
        4,
        4,
        4,
        4,
        4,
        4,
        4,
        4,
        4,
        4,
        4,
        4,
        4,
        4,
        4,
        4,
        4,
        4,
        4,
        4,
        4,
        4,
        4,
        4,
        4,
        4,
        4,
        4,
        4,
        4,
        4,
        4,
        4,
        4,
        4,
        4,
        4,
        4,
        4,
        4,
        4,
        4,
        4,
        4,
        4,
        4,
        4,
        4,
        4,
        4,
        4,
        4,
        4,
        4,
        4,
        4,
        4,
        4,
        4,
        4,
        4,
        4,
        4,
        4,
        4,
        4,
        4,
        4,
        4,
        4,
        4,
        4,
        4,
        4,
        4,
        4,
        4,
        4,
        4,
        4
    ],
    "frameIds": [
        85262336,
        85262347,
        85262358,
        85262369,
        85262380,
        85262391,
        85262402,
        85262413,
        85262424,
        85262337,
        85262338,
        85262339,
        85262340,
        85262341,
        85262342,
        85262343,
        85262344,
        85262345,
        85262346,
        85262348,
        85262349,
        85262350,
        85262351,
        85262352,
        85262353,
        85262354,
        85262355,
        85262356,
        85262357,
        85262359,
        85262360,
        85262361,
        85262362,
        85262363,
        85262364,
        85262365,
        85262366,
        85262367,
        85262368,
        85262370,
        85262371,
        85262372,
        85262373,
        85262374,
        85262375,
        85262376,
        85262377,
        85262378,
        85262379,
        85262381,
        85262382,
        85262383,
        85262384,
        85262385,
        85262386,
        85262387,
        85262388,
        85262389,
        85262390,
        85262392,
        85262393,
        85262394,
        85262395,
        85262396,
        85262397,
        85262398,
        85262399,
        85262400,
        85262401,
        85262403,
        85262404,
        85262405,
        85262406,
        85262407,
        85262408,
        85262409,
        85262410,
        85262411,
        85262412,
        85262414,
        85262415,
        85262416,
        85262417,
        85262418,
        85262419,
        85262420,
        85262421,
        85262422,
        85262423,
        85262425,
        85262426,
        85262427,
        85262428,
        85262429,
        85262430,
        85262431
    ],
    "chatFrameIds": [
    ]
}