{
    "id": 4989,
    "field2079": -1,
    "field2082": 0,
    "field2083": 0,
    "frameCount": -1,
    "field2091": true,
    "field2092": 6,
    "shield": -1,
    "weapon": -1,
    "field2095": 99,
    "field2096": -1,
    "field2097": -1,
    "field2078": 2,
    "frameLengths": [
        5,
        5,
        4,
        3,
        5,
        2,
        3,
        3,
        3,
        5,
        7,
        6,
        6,
        5,
        3,
        2,
        3,
        5,
        5,
        5,
        5,
        5,
        5,
        500
    ],
    "frameIds": [
        37618178,
        37618189,
        37618193,
        37618194,
        37618195,
        37618196,
        37618197,
        37618198,
        37618199,
        37618179,
        37618180,
        37618181,
        37618182,
        37618183,
        37618184,
        37618185,
        37618186,
        37618187,
        37618188,
        37618190,
        37618191,
        37618190,
        37618190,
        37618190
    ],
    "chatFrameIds": [
    ]
}