{
    "id": 5876,
    "field2079": -1,
    "field2082": 0,
    "field2083": 0,
    "frameCount": -1,
    "field2091": false,
    "field2092": 5,
    "shield": -1,
    "weapon": -1,
    "field2095": 99,
    "field2096": -1,
    "field2097": -1,
    "field2078": 2,
    "frameLengths": [
        3,
        3,
        3,
        3,
        3,
        3,
        3,
        3,
        3,
        3,
        3,
        3,
        3,
        3,
        3,
        3
    ],
    "frameIds": [
        95223909,
        95223918,
        95223919,
        95223920,
        95223921,
        95223922,
        95223923,
        95223924,
        95223925,
        95223911,
        95223912,
        95223913,
        95223914,
        95223915,
        95223916,
        95223917
    ],
    "chatFrameIds": [
    ]
}