{
    "id": 5878,
    "field2079": -1,
    "field2082": 0,
    "field2083": 0,
    "frameCount": -1,
    "field2091": false,
    "field2092": 5,
    "shield": -1,
    "weapon": -1,
    "field2095": 99,
    "field2096": -1,
    "field2097": -1,
    "field2078": 2,
    "frameLengths": [
        3,
        3,
        3,
        3,
        3,
        3,
        3,
        3,
        3,
        3,
        3,
        3,
        3,
        3,
        3,
        3
    ],
    "frameIds": [
        95224382,
        95224390,
        95224391,
        95224392,
        95224393,
        95224394,
        95224395,
        95224396,
        95224397,
        95224383,
        95224384,
        95224385,
        95224386,
        95224387,
        95224388,
        95224389
    ],
    "chatFrameIds": [
    ]
}