{
    "id": 6097,
    "field2079": -1,
    "field2082": 0,
    "field2083": 0,
    "frameCount": -1,
    "field2091": false,
    "field2092": 5,
    "shield": -1,
    "weapon": -1,
    "field2095": 99,
    "field2096": -1,
    "field2097": -1,
    "field2078": 2,
    "frameLengths": [
        4,
        4,
        4,
        4,
        4,
        4,
        4,
        4,
        4,
        4,
        4,
        4,
        4,
        4,
        4,
        4,
        4,
        4,
        4,
        4,
        4,
        4,
        4,
        4,
        4,
        4,
        4,
        4,
        4,
        4
    ],
    "frameIds": [
        95289344,
        95289355,
        95289366,
        95289368,
        95289369,
        95289370,
        95289371,
        95289372,
        95289373,
        95289345,
        95289346,
        95289347,
        95289348,
        95289349,
        95289350,
        95289351,
        95289352,
        95289353,
        95289354,
        95289356,
        95289357,
        95289358,
        95289359,
        95289360,
        95289361,
        95289362,
        95289363,
        95289364,
        95289365,
        95289367
    ],
    "chatFrameIds": [
    ]
}