{
    "id": 6103,
    "field2079": -1,
    "field2082": 0,
    "field2083": 0,
    "frameCount": -1,
    "field2091": true,
    "field2092": 5,
    "shield": -1,
    "weapon": -1,
    "field2095": 99,
    "field2096": -1,
    "field2097": -1,
    "field2078": 2,
    "frameLengths": [
        3,
        3,
        3,
        3,
        3,
        3,
        3,
        3,
        3,
        3,
        3,
        3,
        3,
        3,
        4
    ],
    "frameIds": [
        95486039,
        95486045,
        95486046,
        95486047,
        95486048,
        95486049,
        95486050,
        95486051,
        95486052,
        95486023,
        95486040,
        95486041,
        95486042,
        95486043,
        95486044
    ],
    "chatFrameIds": [
    ]
}