{
    "id": 6230,
    "field2079": -1,
    "field2082": 0,
    "field2083": 0,
    "frameCount": -1,
    "field2091": false,
    "field2092": 10,
    "shield": -1,
    "weapon": -1,
    "field2095": 99,
    "field2096": -1,
    "field2097": -1,
    "field2078": 2,
    "frameLengths": [
        4,
        4,
        4,
        4,
        4,
        4,
        4,
        4,
        3,
        3,
        3,
        4,
        4,
        4,
        4,
        4,
        4,
        4,
        4,
        4,
        4,
        4,
        4,
        4,
        4,
        4,
        4,
        4,
        4,
        4,
        4,
        4,
        4,
        3,
        3,
        3,
        3,
        3,
        3,
        3,
        3,
        3,
        3,
        3,
        200
    ],
    "frameIds": [
        103940364,
        103940375,
        103940386,
        103940398,
        103940405,
        103940406,
        103940407,
        103940408,
        103940409,
        103940365,
        103940366,
        103940367,
        103940368,
        103940369,
        103940370,
        103940371,
        103940372,
        103940373,
        103940374,
        103940376,
        103940377,
        103940378,
        103940379,
        103940380,
        103940381,
        103940382,
        103940383,
        103940384,
        103940385,
        103940387,
        103940388,
        103940389,
        103940390,
        103940392,
        103940393,
        103940394,
        103940395,
        103940396,
        103940397,
        103940399,
        103940400,
        103940401,
        103940402,
        103940403,
        103940404
    ],
    "chatFrameIds": [
    ]
}