{
    "id": 6353,
    "field2079": -1,
    "field2082": 0,
    "field2083": 0,
    "frameCount": -1,
    "field2091": false,
    "field2092": 5,
    "shield": -1,
    "weapon": -1,
    "field2095": 99,
    "field2096": -1,
    "field2097": -1,
    "field2078": 2,
    "frameLengths": [
        40,
        6,
        6,
        6,
        6,
        6,
        6,
        6,
        6,
        6,
        6,
        6,
        6,
        6,
        6,
        6,
        6,
        6,
        6,
        6,
        6,
        6,
        6,
        6,
        6,
        6,
        11
    ],
    "frameIds": [
        105578496,
        105578497,
        105578507,
        105578519,
        105578516,
        105578520,
        105578517,
        105578521,
        105578518,
        105578522,
        105578508,
        105578509,
        105578510,
        105578511,
        105578512,
        105578513,
        105578514,
        105578515,
        105578498,
        105578499,
        105578500,
        105578501,
        105578502,
        105578503,
        105578504,
        105578505,
        105578506
    ],
    "chatFrameIds": [
    ]
}