{
    "id": 6373,
    "field2079": -1,
    "field2082": 0,
    "field2083": 0,
    "frameCount": -1,
    "field2091": false,
    "field2092": 5,
    "shield": -1,
    "weapon": -1,
    "field2095": 99,
    "field2096": -1,
    "field2097": -1,
    "field2078": 2,
    "frameLengths": [
        4,
        4,
        4,
        4,
        4,
        4,
        4,
        4,
        4,
        4,
        4,
        4,
        4,
        4,
        4,
        4
    ],
    "frameIds": [
        107413623,
        107413638,
        107413631,
        107413624,
        107413632,
        107413625,
        107413633,
        107413626,
        107413634,
        107413627,
        107413635,
        107413628,
        107413636,
        107413629,
        107413637,
        107413630
    ],
    "chatFrameIds": [
    ]
}