{
    "id": 6399,
    "field2079": -1,
    "field2082": 0,
    "field2083": 0,
    "frameCount": -1,
    "field2091": true,
    "field2092": 5,
    "shield": -1,
    "weapon": -1,
    "field2095": 99,
    "field2096": -1,
    "field2097": -1,
    "field2078": 2,
    "frameLengths": [
        5,
        5,
        5,
        5,
        5,
        5,
        5,
        5,
        5,
        5,
        5,
        5,
        5,
        5,
        5,
        5,
        5,
        5,
        5,
        5,
        5,
        5,
        5,
        5,
        5,
        5,
        5,
        5,
        5,
        5,
        5,
        5,
        5,
        5,
        5,
        5,
        5,
        5,
        5,
        5,
        5,
        5,
        5,
        5,
        5,
        5,
        5,
        5
    ],
    "frameIds": [
        107282635,
        107282646,
        107282652,
        107282653,
        107282654,
        107282655,
        107282656,
        107282657,
        107282658,
        107282636,
        107282637,
        107282638,
        107282639,
        107282640,
        107282641,
        107282642,
        107282643,
        107282644,
        107282645,
        107282647,
        107282648,
        107282649,
        107282650,
        107282651,
        107282650,
        107282651,
        107282650,
        107282649,
        107282648,
        107282647,
        107282645,
        107282644,
        107282643,
        107282642,
        107282641,
        107282640,
        107282639,
        107282638,
        107282637,
        107282636,
        107282658,
        107282657,
        107282656,
        107282655,
        107282654,
        107282653,
        107282652,
        107282646
    ],
    "chatFrameIds": [
    ]
}