{
    "id": 6410,
    "field2079": -1,
    "field2082": 0,
    "field2083": 0,
    "frameCount": -1,
    "field2091": false,
    "field2092": 5,
    "shield": -1,
    "weapon": -1,
    "field2095": 99,
    "field2096": -1,
    "field2097": -1,
    "field2078": 2,
    "frameLengths": [
        3,
        3,
        3,
        3,
        3,
        3,
        3,
        3,
        3,
        3,
        3,
        3,
        3,
        3,
        3,
        3
    ],
    "frameIds": [
        107741184,
        107741192,
        107741193,
        107741194,
        107741195,
        107741196,
        107741197,
        107741198,
        107741199,
        107741185,
        107741186,
        107741187,
        107741188,
        107741189,
        107741190,
        107741191
    ],
    "chatFrameIds": [
    ]
}