{
    "id": 6759,
    "field2079": -1,
    "field2082": 0,
    "field2083": 0,
    "frameCount": -1,
    "field2091": false,
    "field2092": 5,
    "shield": -1,
    "weapon": -1,
    "field2095": 99,
    "field2096": -1,
    "field2097": -1,
    "field2078": 2,
    "frameLengths": [
        5,
        5,
        5,
        5,
        5,
        5,
        5,
        5,
        5,
        5,
        5,
        5,
        5,
        5,
        5,
        5,
        5,
        5,
        5,
        5,
        5,
        5,
        5
    ],
    "frameIds": [
        112132323,
        112132207,
        112132521,
        112132206,
        112132511,
        112132239,
        112132542,
        112132574,
        112132272,
        112132429,
        112132210,
        112132498,
        112132493,
        112132125,
        112132399,
        112132571,
        112132216,
        112132533,
        112132217,
        112132293,
        112132465,
        112132538,
        112132390
    ],
    "chatFrameIds": [
    ]
}