{
    "id": 7396,
    "field2079": -1,
    "field2082": 0,
    "field2083": 0,
    "frameCount": -1,
    "field2091": false,
    "field2092": 5,
    "shield": -1,
    "weapon": -1,
    "field2095": 99,
    "field2096": -1,
    "field2097": -1,
    "field2078": 2,
    "frameLengths": [
        4,
        4,
        4,
        4,
        3,
        3,
        4,
        4,
        4,
        4,
        3,
        3,
        4,
        4,
        4,
        4
    ],
    "frameIds": [
        123797512,
        123797506,
        123797518,
        123797549,
        123797545,
        123797532,
        123797529,
        123797514,
        123797507,
        123797522,
        123797533,
        123797526,
        123797516,
        123797527,
        123797539,
        123797520
    ],
    "chatFrameIds": [
    ]
}