{
    "id": 7439,
    "field2079": -1,
    "field2082": 0,
    "field2083": 0,
    "frameCount": -1,
    "field2091": false,
    "field2092": 5,
    "shield": -1,
    "weapon": -1,
    "field2095": 99,
    "field2096": -1,
    "field2097": -1,
    "field2078": 2,
    "frameLengths": [
        4,
        4,
        4,
        4,
        4,
        4,
        4,
        4,
        4,
        4,
        4,
        4,
        4,
        4,
        4
    ],
    "frameIds": [
        123338866,
        123339083,
        123338941,
        123338899,
        123338778,
        123339005,
        123338956,
        123339002,
        123339042,
        123338929,
        123338936,
        123338876,
        123339007,
        123338901,
        123338834
    ],
    "chatFrameIds": [
    ]
}