{
    "id": 7775,
    "field2079": -1,
    "field2082": 0,
    "field2083": 0,
    "frameCount": -1,
    "field2091": false,
    "field2092": 5,
    "shield": -1,
    "weapon": -1,
    "field2095": 99,
    "field2096": -1,
    "field2097": -1,
    "field2078": 2,
    "frameLengths": [
        2,
        2,
        2,
        2,
        2,
        2,
        2,
        2,
        2,
        2,
        2,
        2,
        2,
        2,
        2
    ],
    "frameIds": [
        128778252,
        128778241,
        128778249,
        128778245,
        128778243,
        128778254,
        128778242,
        128778246,
        128778251,
        128778248,
        128778247,
        128778244,
        128778250,
        128778253,
        128778240
    ],
    "chatFrameIds": [
    ]
}