{
    "id": 7806,
    "field2079": -1,
    "field2082": 0,
    "field2083": 0,
    "frameCount": -1,
    "field2091": false,
    "field2092": 5,
    "shield": -1,
    "weapon": -1,
    "field2095": 99,
    "field2096": -1,
    "field2097": -1,
    "field2078": 2,
    "frameLengths": [
        4,
        4,
        5,
        5,
        4,
        4,
        4,
        4,
        5,
        5,
        4,
        4,
        4,
        4,
        4,
        4,
        5,
        5,
        4,
        4,
        4,
        4,
        5,
        5,
        4,
        4,
        4,
        4,
        4,
        4,
        5,
        5,
        4,
        4,
        4,
        4,
        5,
        5,
        4,
        4,
        4,
        4
    ],
    "frameIds": [
        131006481,
        131006471,
        131006465,
        131006528,
        131006484,
        131006512,
        131006531,
        131006515,
        131006533,
        131006527,
        131006540,
        131006473,
        131006480,
        131006516,
        131006493,
        131006534,
        131006506,
        131006532,
        131006525,
        131006475,
        131006514,
        131006536,
        131006467,
        131006545,
        131006542,
        131006476,
        131006499,
        131006541,
        131006501,
        131006483,
        131006538,
        131006497,
        131006490,
        131006479,
        131006491,
        131006543,
        131006539,
        131006504,
        131006526,
        131006503,
        131006486,
        131006487
    ],
    "chatFrameIds": [
    ]
}