{
    "id": 7931,
    "field2079": -1,
    "field2082": 0,
    "field2083": 0,
    "frameCount": 8,
    "field2091": false,
    "field2092": 5,
    "shield": -1,
    "weapon": -1,
    "field2095": 99,
    "field2096": -1,
    "field2097": -1,
    "field2078": 2,
    "frameLengths": [
        6,
        8,
        8,
        8,
        8,
        6,
        6,
        6
    ],
    "frameIds": [
        134086692,
        134086683,
        134086688,
        134086675,
        134086668,
        134086687,
        134086660,
        134086690
    ],
    "chatFrameIds": [
    ]
}