{
    "id": 8010,
    "field2079": -1,
    "field2082": 0,
    "field2083": 0,
    "frameCount": -1,
    "field2091": true,
    "field2092": 5,
    "shield": -1,
    "weapon": -1,
    "field2095": 99,
    "field2096": -1,
    "field2097": -1,
    "field2078": 2,
    "frameLengths": [
        2,
        2,
        2,
        2,
        3,
        2,
        2,
        3,
        3,
        4,
        3,
        3,
        3,
        3,
        3,
        3,
        4,
        4,
        5,
        4
    ],
    "frameIds": [
        137101377,
        137101328,
        137101339,
        137101376,
        137101331,
        137101325,
        137101365,
        137101319,
        137101313,
        137101337,
        137101335,
        137101375,
        137101356,
        137101364,
        137101360,
        137101324,
        137101373,
        137101374,
        137101352,
        137101326
    ],
    "chatFrameIds": [
    ]
}