{
    "id": 8083,
    "field2079": -1,
    "field2082": 0,
    "field2083": 0,
    "frameCount": -1,
    "field2091": false,
    "field2092": 5,
    "shield": -1,
    "weapon": -1,
    "field2095": 99,
    "field2096": -1,
    "field2097": -1,
    "field2078": 2,
    "frameLengths": [
        4,
        4,
        4,
        3,
        4,
        4,
        4,
        3,
        4,
        4,
        4,
        3,
        4,
        4,
        4,
        3
    ],
    "frameIds": [
        141754382,
        141754374,
        141754371,
        141754368,
        141754370,
        141754377,
        141754375,
        141754378,
        141754372,
        141754369,
        141754383,
        141754379,
        141754381,
        141754380,
        141754376,
        141754373
    ],
    "chatFrameIds": [
    ]
}