{
    "id": 8112,
    "field2079": -1,
    "field2082": 0,
    "field2083": 0,
    "frameCount": 1,
    "field2091": false,
    "field2092": 11,
    "shield": -1,
    "weapon": -1,
    "field2095": 99,
    "field2096": -1,
    "field2097": -1,
    "field2078": 2,
    "frameLengths": [
        3,
        3,
        3,
        4,
        4,
        4,
        4,
        4,
        5,
        3,
        3,
        4,
        4,
        3,
        3,
        3,
        3,
        3,
        3,
        3,
        3,
        3,
        3,
        3,
        3,
        3,
        3,
        3,
        3,
        3,
        3,
        3,
        3,
        3,
        3,
        3,
        3,
        3,
        3,
        3,
        3,
        3,
        3,
        3,
        3,
        3,
        3,
        3,
        3,
        3,
        3,
        3,
        3,
        3,
        3,
        3,
        3,
        3,
        3,
        3,
        3,
        3,
        3,
        3,
        3,
        3,
        3,
        3,
        3,
        3,
        3,
        3,
        3,
        3,
        3,
        3,
        3,
        3,
        3,
        3,
        3,
        3,
        3,
        3,
        3,
        3,
        3,
        3,
        3,
        3,
        3,
        3,
        3,
        3,
        3,
        3,
        3,
        3,
        3,
        3,
        3,
        3,
        3,
        3,
        3,
        3,
        3,
        3,
        3,
        3,
        3,
        3,
        3,
        3,
        3,
        3,
        3,
        3,
        3,
        3,
        3,
        3,
        3,
        3,
        3,
        3,
        3,
        3,
        3,
        3,
        3,
        4
    ],
    "frameIds": [
        139329543,
        139329586,
        139329558,
        139329549,
        139329584,
        139329591,
        139329545,
        139329564,
        139329544,
        139329581,
        139329563,
        139329540,
        139329556,
        139329575,
        139329574,
        139329582,
        139329536,
        139329583,
        139329542,
        139329571,
        139329547,
        139329577,
        139329588,
        139329570,
        139329538,
        139329548,
        139329562,
        139329561,
        139329553,
        139329541,
        139329557,
        139329569,
        139329576,
        139329589,
        139329560,
        139329579,
        139329580,
        139329572,
        139329554,
        139329546,
        139329551,
        139329555,
        139329565,
        139329552,
        139329539,
        139329578,
        139329568,
        139329573,
        139329537,
        139329585,
        139329587,
        139329590,
        139329566,
        139329550,
        139329559,
        139329567,
        139329572,
        139329554,
        139329546,
        139329551,
        139329555,
        139329565,
        139329552,
        139329539,
        139329578,
        139329568,
        139329573,
        139329537,
        139329585,
        139329587,
        139329590,
        139329566,
        139329550,
        139329559,
        139329567,
        139329572,
        139329554,
        139329546,
        139329551,
        139329555,
        139329565,
        139329552,
        139329539,
        139329578,
        139329568,
        139329573,
        139329537,
        139329585,
        139329587,
        139329590,
        139329566,
        139329550,
        139329559,
        139329567,
        139329572,
        139329554,
        139329546,
        139329551,
        139329555,
        139329565,
        139329552,
        139329539,
        139329578,
        139329568,
        139329573,
        139329537,
        139329585,
        139329587,
        139329590,
        139329566,
        139329550,
        139329559,
        139329567,
        139329572,
        139329554,
        139329546,
        139329551,
        139329555,
        139329565,
        139329552,
        139329539,
        139329578,
        139329568,
        139329573,
        139329537,
        139329585,
        139329587,
        139329590,
        139329566,
        139329550,
        139329559,
        139329567
    ],
    "chatFrameIds": [
    ]
}