{
    "id": 8148,
    "field2079": -1,
    "field2082": 0,
    "field2083": 0,
    "frameCount": 16,
    "field2091": false,
    "field2092": 5,
    "shield": -1,
    "weapon": -1,
    "field2095": 99,
    "field2096": -1,
    "field2097": -1,
    "field2078": 2,
    "frameLengths": [
        4,
        4,
        4,
        4,
        4,
        4,
        4,
        4,
        4,
        4,
        4,
        4,
        4,
        4,
        4,
        4
    ],
    "frameIds": [
        145555461,
        145555464,
        145555467,
        145555470,
        145555457,
        145555460,
        145555459,
        145555456,
        145555471,
        145555466,
        145555469,
        145555462,
        145555468,
        145555463,
        145555458,
        145555465
    ],
    "chatFrameIds": [
    ]
}