{
    "id": 825,
    "field2079": -1,
    "field2082": 0,
    "field2083": 0,
    "frameCount": -1,
    "field2091": false,
    "field2092": 5,
    "shield": -1,
    "weapon": -1,
    "field2095": 99,
    "field2096": -1,
    "field2097": -1,
    "field2078": 2,
    "frameLengths": [
        20,
        20,
        20,
        20,
        20,
        20,
        20,
        20,
        20,
        20,
        20,
        20
    ],
    "frameIds": [
        13697176,
        13697180,
        13697181,
        13697182,
        13697183,
        13697184,
        13697185,
        13697186,
        13697187,
        13697177,
        13697178,
        13697179
    ],
    "chatFrameIds": [
    ]
}