{
    "id": 8529,
    "field2079": -1,
    "field2082": 0,
    "field2083": 0,
    "frameCount": -1,
    "field2091": false,
    "field2092": 5,
    "shield": -1,
    "weapon": -1,
    "field2095": 99,
    "field2096": -1,
    "field2097": -1,
    "field2078": 2,
    "frameLengths": [
        5,
        5,
        5,
        3,
        5,
        4,
        4,
        8,
        4,
        4,
        2,
        2,
        2
    ],
    "frameIds": [
        157286407,
        157286409,
        157286403,
        157286406,
        157286402,
        157286410,
        157286401,
        157286400,
        157286408,
        157286412,
        157286405,
        157286404,
        157286411
    ],
    "chatFrameIds": [
    ]
}