{
    "id": 8850,
    "field2079": -1,
    "field2082": 0,
    "field2083": 0,
    "frameCount": 64,
    "field2091": false,
    "field2092": 5,
    "shield": -1,
    "weapon": -1,
    "field2095": 99,
    "field2096": -1,
    "field2097": -1,
    "field2078": 2,
    "frameLengths": [
        2,
        2,
        2,
        2,
        2,
        2,
        2,
        2,
        2,
        2,
        2,
        2,
        2,
        2,
        2,
        2,
        2,
        2,
        2,
        2,
        2,
        2,
        2,
        2,
        2,
        2,
        2,
        2,
        2,
        2,
        2,
        2,
        2,
        2,
        2,
        2,
        2,
        2,
        2,
        2,
        2,
        2,
        2,
        2,
        2,
        2,
        2,
        2,
        2,
        2,
        2,
        2,
        2,
        2,
        2,
        2,
        2,
        2,
        2,
        2,
        2,
        2,
        2,
        2
    ],
    "frameIds": [
        169017371,
        169017358,
        169017376,
        169017359,
        169017362,
        169017372,
        169017356,
        169017370,
        169017381,
        169017350,
        169017369,
        169017400,
        169017386,
        169017345,
        169017351,
        169017347,
        169017363,
        169017373,
        169017401,
        169017360,
        169017399,
        169017349,
        169017404,
        169017387,
        169017393,
        169017375,
        169017355,
        169017389,
        169017405,
        169017397,
        169017388,
        169017403,
        169017367,
        169017361,
        169017374,
        169017391,
        169017396,
        169017348,
        169017365,
        169017357,
        169017354,
        169017352,
        169017407,
        169017380,
        169017368,
        169017406,
        169017384,
        169017395,
        169017377,
        169017379,
        169017346,
        169017383,
        169017390,
        169017364,
        169017366,
        169017382,
        169017344,
        169017398,
        169017378,
        169017394,
        169017353,
        169017402,
        169017385,
        169017392
    ],
    "chatFrameIds": [
    ]
}