{
    "id": 8894,
    "field2079": -1,
    "field2082": 0,
    "field2083": 0,
    "frameCount": 10,
    "field2091": false,
    "field2092": 5,
    "shield": -1,
    "weapon": -1,
    "field2095": 99,
    "field2096": -1,
    "field2097": -1,
    "field2078": 2,
    "frameLengths": [
        5,
        5,
        5,
        5,
        5,
        5,
        5,
        5,
        5,
        5
    ],
    "frameIds": [
        171376648,
        171376650,
        171376647,
        171376649,
        171376645,
        171376641,
        171376640,
        171376643,
        171376651,
        171376646
    ],
    "chatFrameIds": [
    ]
}