{
    "id": 9202,
    "field2079": -1,
    "field2082": 0,
    "field2083": 0,
    "frameCount": 42,
    "field2091": false,
    "field2092": 5,
    "shield": -1,
    "weapon": -1,
    "field2095": 99,
    "field2096": -1,
    "field2097": -1,
    "field2078": 2,
    "frameLengths": [
        3,
        3,
        3,
        3,
        3,
        3,
        3,
        3,
        3,
        3,
        3,
        3,
        3,
        3,
        3,
        3,
        3,
        3,
        3,
        3,
        3,
        3,
        3,
        3,
        3,
        3,
        3,
        3,
        3,
        3,
        3,
        3,
        3,
        3,
        3,
        3,
        3,
        3,
        3,
        3,
        3,
        3
    ],
    "frameIds": [
        183238675,
        183238693,
        183238685,
        183238663,
        183238676,
        183238682,
        183238661,
        183238657,
        183238694,
        183238674,
        183238668,
        183238692,
        183238680,
        183238667,
        183238686,
        183238691,
        183238697,
        183238688,
        183238658,
        183238665,
        183238656,
        183238671,
        183238670,
        183238669,
        183238695,
        183238690,
        183238677,
        183238666,
        183238672,
        183238659,
        183238683,
        183238684,
        183238696,
        183238664,
        183238679,
        183238660,
        183238689,
        183238687,
        183238678,
        183238681,
        183238673,
        183238662
    ],
    "chatFrameIds": [
    ]
}