{
    "id": 9248,
    "field2079": -1,
    "field2082": 0,
    "field2083": 0,
    "frameCount": -1,
    "field2091": false,
    "field2092": 5,
    "shield": -1,
    "weapon": -1,
    "field2095": 99,
    "field2096": -1,
    "field2097": -1,
    "field2078": 2,
    "frameLengths": [
        10,
        10,
        10,
        10,
        10,
        10,
        10,
        10
    ],
    "frameIds": [
        185663490,
        185663489,
        185663495,
        185663494,
        185663488,
        185663491,
        185663493,
        185663492
    ],
    "chatFrameIds": [
    ]
}