{
    "id": 9254,
    "field2079": -1,
    "field2082": 0,
    "field2083": 0,
    "frameCount": -1,
    "field2091": false,
    "field2092": 5,
    "shield": -1,
    "weapon": -1,
    "field2095": 99,
    "field2096": -1,
    "field2097": -1,
    "field2078": 2,
    "frameLengths": [
        10,
        10,
        10,
        10,
        10,
        10,
        10,
        10
    ],
    "frameIds": [
        185597956,
        185597952,
        185597953,
        185597958,
        185597959,
        185597954,
        185597957,
        185597955
    ],
    "chatFrameIds": [
    ]
}