{
    "id": 9276,
    "field2079": -1,
    "field2082": 0,
    "field2083": 0,
    "frameCount": -1,
    "field2091": false,
    "field2092": 4,
    "shield": -1,
    "weapon": -1,
    "field2095": 99,
    "field2096": -1,
    "field2097": -1,
    "field2078": 2,
    "frameLengths": [
        8,
        7,
        7,
        7,
        7,
        7,
        7,
        8,
        8,
        8,
        8,
        8
    ],
    "frameIds": [
        186712070,
        186712073,
        186712067,
        186712074,
        186712069,
        186712072,
        186712066,
        186712075,
        186712065,
        186712071,
        186712064,
        186712068
    ],
    "chatFrameIds": [
    ]
}