{
    "id": 3584,
    "params": {
        "1313": "Corrupted Hunllef",
        "1314": 894,
        "1315": 19,
        "1319": "The Corrupted Hunllef is the boss located within The Corrupted Gauntlet, an activity within the elven capital city of Prifddinas.<br><br>Access to The Corrupted Gauntlet is unlocked by completing The Gauntlet.<br><br>Attack Styles - Ranged, Magic, Special<br>Immunities - Poison, Venom<br>Slayer categories - None",
        "1320": "Mandatory requirements:<br> - Song of the Elves<br> - Access to The Corrupted Gauntlet<br><br>Combat Achievement task difficulty:<br> - Elite<br> - Master<br> - Grandmaster",
        "1317": 52893668,
        "1318": 13,
        "1322": 38595,
        "1323": 8417,
        "1324": 35,
        "1325": 270,
        "1326": 94,
        "1327": 185,
        "1328": 0,
        "1329": 2400
    }
}