{
    "id": 727,
    "params": {
        "879": "Hardcore Harvester",
        "880": "- You receive 3 times the normal amount of resources from Mining, Fishing, Woodcutting, Harvesting Herbs, Blast Mining and Farming Contracts. These additional resources do not grant bonus XP.<br>- You receive 3 times as many Molch Pearls from Aerial Fishing.<br>- Farming cycles occur every 1 minute instead of every 5 minutes.",
        "884": 2329,
        "881": 2361,
        "883": 2362,
        "885": 1,
        "1274": 3047
    }
}