{
    "id": 26477,
    "model": 43449,
    "name": "Void melee helm (or)",
    "zoom2d": 720,
    "xan2d": 69,
    "yan2d": 201,
    "zan2d": 0,
    "offsetX2d": 4,
    "offsetY2d": -5,
    "isStackable": 0,
    "price": 9851,
    "isMembersOnly": true,
    "groundActions": [
        "null",
        "null",
        "Take",
        "null",
        "null"
    ],
    "inventoryActions": [
        "null",
        "Wear",
        "Dismantle",
        "null",
        "Drop"
    ],
    "shiftClickIndex": -2,
    "maleModel": 43254,
    "maleModel1": -1,
    "maleOffset": 0,
    "femaleModel": 43285,
    "femaleModel1": -1,
    "femaleOffset": 0,
    "maleModel2": -1,
    "femaleModel2": -1,
    "maleHeadModel": 63,
    "maleHeadModel2": 43403,
    "femaleHeadModel": 120,
    "femaleHeadModel2": 43403,
    "note": -1,
    "noteTemplate": -1,
    "resizeX": 128,
    "resizeY": 128,
    "resizeZ": 128,
    "ambient": 0,
    "contrast": 0,
    "team": 0,
    "isTradable": false,
    "unnotedId": -1,
    "notedId": -1,
    "placeholder": 26478,
    "placeholderTemplate": -1,
    "params": {
    }
}