{
    "id": 7534,
    "model": 13827,
    "name": "Fishbowl helmet",
    "zoom2d": 848,
    "xan2d": 27,
    "yan2d": 1679,
    "zan2d": 0,
    "offsetX2d": 2,
    "offsetY2d": 0,
    "isStackable": 0,
    "price": 1,
    "isMembersOnly": true,
    "groundActions": [
        "null",
        "null",
        "Take",
        "null",
        "null"
    ],
    "inventoryActions": [
        "null",
        "Wear",
        "null",
        "null",
        "Drop"
    ],
    "shiftClickIndex": -2,
    "maleModel": 13333,
    "maleModel1": 13335,
    "maleOffset": 0,
    "femaleModel": 13341,
    "femaleModel1": 13344,
    "femaleOffset": 0,
    "maleModel2": -1,
    "femaleModel2": -1,
    "maleHeadModel": 13871,
    "maleHeadModel2": -1,
    "femaleHeadModel": 13873,
    "femaleHeadModel2": -1,
    "note": -1,
    "noteTemplate": -1,
    "resizeX": 128,
    "resizeY": 128,
    "resizeZ": 128,
    "ambient": 0,
    "contrast": 0,
    "team": 0,
    "isTradable": false,
    "unnotedId": -1,
    "notedId": -1,
    "placeholder": 17393,
    "placeholderTemplate": -1,
    "params": {
    }
}